whool/__init__.py
whool/__main__.py
whool/buildapi.py
whool/cli.py
whool/compat.py
whool/init.py
whool/py.typed
whool/utils.py
whool/version.py
whool-1.3.dist-info/METADATA
whool-1.3.dist-info/WHEEL
whool-1.3.dist-info/entry_points.txt
whool-1.3.dist-info/licenses/LICENSE
whool-1.3.dist-info/RECORD
