Metadata-Version: 2.4
Name: whool
Version: 1.3
Summary: whool - build backend for Odoo addons
Project-URL: Homepage, https://github.com/sbidoul/whool
Project-URL: Documentation, https://github.com/sbidoul/whool
Project-URL: Changelog, https://github.com/sbidoul/whool/blob/main/CHANGELOG.md
Project-URL: Source, https://github.com/sbidoul/whool
Author-email: Stéphane Bidoul <stephane.bidoul@gmail.com>
License-File: LICENSE
Classifier: Development Status :: 5 - Production/Stable
Classifier: Framework :: Odoo
Classifier: License :: OSI Approved :: MIT License
Requires-Python: >=3.7
Requires-Dist: importlib-metadata; python_version < '3.8'
Requires-Dist: manifestoo-core>=1.1
Requires-Dist: tomli; python_version < '3.11'
Requires-Dist: wheel
Provides-Extra: test
Requires-Dist: coverage[toml]; extra == 'test'
Requires-Dist: mypy; extra == 'test'
Requires-Dist: pytest; extra == 'test'
Requires-Dist: pytest-cov; extra == 'test'
